[
  {
    "referrer": "github.com",
    "count": 815,
    "uniques": 121
  },
  {
    "referrer": "paperswithcode.com",
    "count": 408,
    "uniques": 70
  },
  {
    "referrer": "Google",
    "count": 275,
    "uniques": 62
  },
  {
    "referrer": "link.zhihu.com",
    "count": 59,
    "uniques": 11
  },
  {
    "referrer": "huggingface.co",
    "count": 30,
    "uniques": 15
  },
  {
    "referrer": "notebooks.githubusercontent.com",
    "count": 6,
    "uniques": 3
  },
  {
    "referrer": "pythonrepo.com",
    "count": 5,
    "uniques": 1
  },
  {
    "referrer": "l.facebook.com",
    "count": 4,
    "uniques": 2
  },
  {
    "referrer": "yandex.ru",
    "count": 4,
    "uniques": 1
  },
  {
    "referrer": "ftz7fmoawa.feishu.cn",
    "count": 2,
    "uniques": 1
  }
]