[
  {
    "referrer": "github.com",
    "count": 1114,
    "uniques": 156
  },
  {
    "referrer": "Google",
    "count": 544,
    "uniques": 117
  },
  {
    "referrer": "paperswithcode.com",
    "count": 459,
    "uniques": 100
  },
  {
    "referrer": "huggingface.co",
    "count": 78,
    "uniques": 18
  },
  {
    "referrer": "link.zhihu.com",
    "count": 33,
    "uniques": 13
  },
  {
    "referrer": "arxiv.org",
    "count": 22,
    "uniques": 3
  },
  {
    "referrer": "l.facebook.com",
    "count": 14,
    "uniques": 1
  },
  {
    "referrer": "zhihu.com",
    "count": 12,
    "uniques": 2
  },
  {
    "referrer": "hub.xn--p8jhe.tw",
    "count": 10,
    "uniques": 2
  },
  {
    "referrer": "cn.bing.com",
    "count": 5,
    "uniques": 5
  }
]