[
  {
    "referrer": "github.com",
    "count": 808,
    "uniques": 74
  },
  {
    "referrer": "paperswithcode.com",
    "count": 475,
    "uniques": 85
  },
  {
    "referrer": "Google",
    "count": 178,
    "uniques": 93
  },
  {
    "referrer": "link.zhihu.com",
    "count": 14,
    "uniques": 4
  },
  {
    "referrer": "Baidu",
    "count": 6,
    "uniques": 4
  },
  {
    "referrer": "nlpprogress.com",
    "count": 2,
    "uniques": 2
  },
  {
    "referrer": "ss.scnu.edu.cn",
    "count": 1,
    "uniques": 1
  },
  {
    "referrer": "StartPage",
    "count": 1,
    "uniques": 1
  },
  {
    "referrer": "html.duckduckgo.com",
    "count": 1,
    "uniques": 1
  },
  {
    "referrer": "linkedin.com",
    "count": 1,
    "uniques": 1
  }
]