[
  {
    "referrer": "Google",
    "count": 1517,
    "uniques": 133
  },
  {
    "referrer": "github.com",
    "count": 1459,
    "uniques": 124
  },
  {
    "referrer": "paperswithcode.com",
    "count": 373,
    "uniques": 54
  },
  {
    "referrer": "huggingface.co",
    "count": 298,
    "uniques": 41
  },
  {
    "referrer": "yangheng-pyabsa.hf.space",
    "count": 261,
    "uniques": 17
  },
  {
    "referrer": "pyabsa.readthedocs.io",
    "count": 174,
    "uniques": 14
  },
  {
    "referrer": "notebooks.githubusercontent.com",
    "count": 80,
    "uniques": 8
  },
  {
    "referrer": "cn.bing.com",
    "count": 69,
    "uniques": 7
  },
  {
    "referrer": "link.zhihu.com",
    "count": 45,
    "uniques": 10
  },
  {
    "referrer": "medium.com",
    "count": 30,
    "uniques": 1
  }
]