[
  {
    "path": "/yangheng95/PyABSA",
    "title": "yangheng95/PyABSA: Open Framework for Aspect-based Sentiment Analysis based o...",
    "count": 822,
    "uniques": 292
  },
  {
    "path": "/yangheng95/PyABSA/issues",
    "title": "关于版本更新的内容的详细说明帮助 · Issue #210 · yangheng95/PyABSA",
    "count": 202,
    "uniques": 32
  },
  {
    "path": "/yangheng95/PyABSA/tree/release/demos",
    "title": "yangheng95/PyABSA: Open Framework for Aspect-based Sentiment Analysis based o...",
    "count": 133,
    "uniques": 54
  },
  {
    "path": "/yangheng95/PyABSA/tree/release/pyabsa",
    "title": "yangheng95/PyABSA: Open Framework for Aspect-based Sentiment Analysis based o...",
    "count": 127,
    "uniques": 39
  },
  {
    "path": "/yangheng95/PyABSA/tree/release/demos/aspect_term_extraction",
    "title": "PyABSA/demos at release · yangheng95/PyABSA",
    "count": 122,
    "uniques": 47
  },
  {
    "path": "/yangheng95/PyABSA/tree/release/demos/aspect_polarity_classification",
    "title": "PyABSA/run_fast_lsa_deberta_large.py 发布时 · yangheng95/PyABSA",
    "count": 113,
    "uniques": 48
  },
  {
    "path": "/yangheng95/PyABSA/blob/release/demos/aspect_polarity_classification/run_fast_lsa_deberta_large.py",
    "title": "PyABSA/run_fast_lsa_deberta_large.py at release · yangheng95/PyABSA · GitHub",
    "count": 83,
    "uniques": 52
  },
  {
    "path": "/yangheng95/PyABSA/tree/release/pyabsa/core",
    "title": "PyABSA/pyabsa/core at release · yangheng95/PyABSA · GitHub",
    "count": 64,
    "uniques": 18
  },
  {
    "path": "/yangheng95/PyABSA/search",
    "title": "Search · senta · GitHub",
    "count": 60,
    "uniques": 16
  },
  {
    "path": "/yangheng95/PyABSA/tree/release/pyabsa/core/apc",
    "title": "PyABSA/pyabsa/core/apc at release · yangheng95/PyABSA · GitHub",
    "count": 48,
    "uniques": 12
  }
]