[
  {
    "referrer": "Google",
    "count": 743,
    "uniques": 128
  },
  {
    "referrer": "github.com",
    "count": 546,
    "uniques": 145
  },
  {
    "referrer": "paperswithcode.com",
    "count": 442,
    "uniques": 116
  },
  {
    "referrer": "link.zhihu.com",
    "count": 107,
    "uniques": 19
  },
  {
    "referrer": "youtube.com",
    "count": 62,
    "uniques": 20
  },
  {
    "referrer": "huggingface.co",
    "count": 59,
    "uniques": 20
  },
  {
    "referrer": "pypi.org",
    "count": 50,
    "uniques": 8
  },
  {
    "referrer": "Bing",
    "count": 41,
    "uniques": 4
  },
  {
    "referrer": "yangheng-multilingual-aspect-based-sentim-6aa230e.hf.space",
    "count": 36,
    "uniques": 11
  },
  {
    "referrer": "colab.research.google.com",
    "count": 32,
    "uniques": 4
  }
]