[
  {
    "path": "/yangheng95/PyABSA",
    "title": "yangheng95/PyABSA: Sentiment Analysis, Text Classification, Text Augmentation...",
    "count": 1079,
    "uniques": 461
  },
  {
    "path": "/yangheng95/PyABSA/issues",
    "title": "Issues · yangheng95/PyABSA · GitHub",
    "count": 228,
    "uniques": 44
  },
  {
    "path": "/yangheng95/PyABSA/tree/release",
    "title": "yangheng95/PyABSA at release",
    "count": 162,
    "uniques": 67
  },
  {
    "path": "/yangheng95/PyABSA/tree/v2/pyabsa",
    "title": "PyABSA/pyabsa at v2 · yangheng95/PyABSA · GitHub",
    "count": 155,
    "uniques": 80
  },
  {
    "path": "/yangheng95/PyABSA/search",
    "title": "Search · TPU · GitHub",
    "count": 120,
    "uniques": 18
  },
  {
    "path": "/yangheng95/PyABSA/tree/v2/examples-v2",
    "title": "PyABSA/examples-v2 at v2 · yangheng95/PyABSA · GitHub",
    "count": 76,
    "uniques": 46
  },
  {
    "path": "/yangheng95/PyABSA/tree/release/demos/aspect_term_extraction",
    "title": "PyABSA/demos/aspect_term_extraction at release · yangheng95/PyABSA · GitHub",
    "count": 70,
    "uniques": 28
  },
  {
    "path": "/yangheng95/PyABSA/tree/v2/pyabsa/tasks",
    "title": "PyABSA/pyabsa/tasks at v2 · yangheng95/PyABSA · GitHub",
    "count": 54,
    "uniques": 26
  },
  {
    "path": "/yangheng95/PyABSA/blob/v2/examples-v2/aspect_polarity_classification/Aspect_Sentiment_Classification.ipynb",
    "title": "PyABSA/Aspect_Sentiment_Classification.ipynb at v2 · yangheng95/PyABSA · GitHub",
    "count": 54,
    "uniques": 25
  },
  {
    "path": "/yangheng95/PyABSA/tree/v2/examples-v2/aspect_polarity_classification",
    "title": "PyABSA/examples-v2/aspect_polarity_classification at v2 · yangheng95/PyABSA ·...",
    "count": 51,
    "uniques": 28
  }
]