{
  "count": 2544,
  "uniques": 233,
  "views": [
    {
      "timestamp": "2024-07-21T00:00:00Z",
      "count": 106,
      "uniques": 14
    },
    {
      "timestamp": "2024-07-22T00:00:00Z",
      "count": 595,
      "uniques": 44
    },
    {
      "timestamp": "2024-07-23T00:00:00Z",
      "count": 366,
      "uniques": 37
    },
    {
      "timestamp": "2024-07-24T00:00:00Z",
      "count": 517,
      "uniques": 36
    },
    {
      "timestamp": "2024-07-25T00:00:00Z",
      "count": 300,
      "uniques": 42
    },
    {
      "timestamp": "2024-07-26T00:00:00Z",
      "count": 331,
      "uniques": 42
    },
    {
      "timestamp": "2024-07-27T00:00:00Z",
      "count": 329,
      "uniques": 18
    }
  ]
}