[
  {
    "referrer": "github.com",
    "count": 1448,
    "uniques": 118
  },
  {
    "referrer": "Google",
    "count": 1343,
    "uniques": 109
  },
  {
    "referrer": "huggingface.co",
    "count": 345,
    "uniques": 46
  },
  {
    "referrer": "paperswithcode.com",
    "count": 298,
    "uniques": 38
  },
  {
    "referrer": "yangheng-pyabsa.hf.space",
    "count": 234,
    "uniques": 17
  },
  {
    "referrer": "pyabsa.readthedocs.io",
    "count": 203,
    "uniques": 12
  },
  {
    "referrer": "link.zhihu.com",
    "count": 60,
    "uniques": 10
  },
  {
    "referrer": "cn.bing.com",
    "count": 44,
    "uniques": 8
  },
  {
    "referrer": "pypi.org",
    "count": 41,
    "uniques": 8
  },
  {
    "referrer": "Bing",
    "count": 37,
    "uniques": 7
  }
]