[
  {
    "path": "/yangheng95/PyABSA",
    "title": "yangheng95/PyABSA: Sentiment Analysis, Text Classification, Text Augmentation...",
    "count": 348,
    "uniques": 201
  },
  {
    "path": "/yangheng95/PyABSA/tree/v2/pyabsa",
    "title": "PyABSA/pyabsa at v2 · yangheng95/PyABSA · GitHub",
    "count": 69,
    "uniques": 29
  },
  {
    "path": "/yangheng95/PyABSA/tree/v2",
    "title": "yangheng95/PyABSA: Sentiment Analysis, Text Classification, Text Augmentation...",
    "count": 51,
    "uniques": 21
  },
  {
    "path": "/yangheng95/PyABSA/tree/v2/examples-v2",
    "title": "PyABSA/examples-v2 at v2 · yangheng95/PyABSA · GitHub",
    "count": 41,
    "uniques": 31
  },
  {
    "path": "/yangheng95/PyABSA/tree/v2/pyabsa/tasks",
    "title": "PyABSA/pyabsa/tasks at v2 · yangheng95/PyABSA · GitHub",
    "count": 30,
    "uniques": 11
  },
  {
    "path": "/yangheng95/PyABSA/issues",
    "title": "Issues · yangheng95/PyABSA · GitHub",
    "count": 29,
    "uniques": 14
  },
  {
    "path": "/yangheng95/PyABSA/tree/release",
    "title": "yangheng95/PyABSA at release",
    "count": 21,
    "uniques": 9
  },
  {
    "path": "/yangheng95/PyABSA/tree/v2/pyabsa/tasks/AspectTermExtraction",
    "title": "PyABSA/pyabsa/tasks/AspectTermExtraction at v2 · yangheng95/PyABSA",
    "count": 21,
    "uniques": 3
  },
  {
    "path": "/yangheng95/pyabsa",
    "title": "yangheng95/PyABSA: Sentiment Analysis, Text Classification, Text Augmentation...",
    "count": 20,
    "uniques": 14
  },
  {
    "path": "/yangheng95/PyABSA/blob/release/README.MD",
    "title": "PyABSA/README.MD at release · yangheng95/PyABSA · GitHub",
    "count": 17,
    "uniques": 3
  }
]