[
  {
    "referrer": "github.com",
    "count": 776,
    "uniques": 123
  },
  {
    "referrer": "paperswithcode.com",
    "count": 374,
    "uniques": 66
  },
  {
    "referrer": "Google",
    "count": 187,
    "uniques": 51
  },
  {
    "referrer": "link.zhihu.com",
    "count": 79,
    "uniques": 14
  },
  {
    "referrer": "huggingface.co",
    "count": 50,
    "uniques": 12
  },
  {
    "referrer": "notebooks.githubusercontent.com",
    "count": 13,
    "uniques": 4
  },
  {
    "referrer": "arxiv.org",
    "count": 13,
    "uniques": 2
  },
  {
    "referrer": "colab.research.google.com",
    "count": 12,
    "uniques": 2
  },
  {
    "referrer": "hf.space",
    "count": 7,
    "uniques": 2
  },
  {
    "referrer": "pythonlang.dev",
    "count": 6,
    "uniques": 3
  }
]