[
  {
    "referrer": "github.com",
    "count": 952,
    "uniques": 104
  },
  {
    "referrer": "Google",
    "count": 668,
    "uniques": 98
  },
  {
    "referrer": "paperswithcode.com",
    "count": 437,
    "uniques": 45
  },
  {
    "referrer": "huggingface.co",
    "count": 270,
    "uniques": 45
  },
  {
    "referrer": "pyabsa.readthedocs.io",
    "count": 103,
    "uniques": 9
  },
  {
    "referrer": "yangheng-pyabsa.hf.space",
    "count": 92,
    "uniques": 16
  },
  {
    "referrer": "youtube.com",
    "count": 57,
    "uniques": 28
  },
  {
    "referrer": "Baidu",
    "count": 45,
    "uniques": 1
  },
  {
    "referrer": "pypi.org",
    "count": 35,
    "uniques": 6
  },
  {
    "referrer": "cn.bing.com",
    "count": 29,
    "uniques": 7
  }
]