[
  {
    "path": "/yangheng95/PyABSA",
    "title": "yangheng95/PyABSA: Sentiment Analysis, Text Classification, Text Augmentation...",
    "count": 587,
    "uniques": 284
  },
  {
    "path": "/yangheng95/PyABSA/tree/v2/examples-v2",
    "title": "PyABSA/examples-v2 at v2 · yangheng95/PyABSA · GitHub",
    "count": 307,
    "uniques": 62
  },
  {
    "path": "/yangheng95/PyABSA/tree/v2/pyabsa",
    "title": "PyABSA/pyabsa at v2 · yangheng95/PyABSA · GitHub",
    "count": 287,
    "uniques": 52
  },
  {
    "path": "/yangheng95/PyABSA/tree/v2/examples-v2/aspect_opinion_sentiment_category_extraction",
    "title": "PyABSA/examples-v2/aspect_opinion_sentiment_category_extraction at v2 · yangh...",
    "count": 135,
    "uniques": 31
  },
  {
    "path": "/yangheng95/PyABSA/tree/v2/pyabsa/tasks",
    "title": "PyABSA/pyabsa/tasks at v2 · yangheng95/PyABSA · GitHub",
    "count": 104,
    "uniques": 18
  },
  {
    "path": "/yangheng95/PyABSA/tree/v2/examples-v2/aspect_sentiment_triplet_extration",
    "title": "PyABSA/examples-v2/aspect_sentiment_triplet_extration at v2 · yangheng95/PyABSA",
    "count": 90,
    "uniques": 24
  },
  {
    "path": "/yangheng95/PyABSA/tree/v2",
    "title": "yangheng95/PyABSA: Sentiment Analysis, Text Classification, Text Augmentation...",
    "count": 78,
    "uniques": 33
  },
  {
    "path": "/yangheng95/PyABSA/issues",
    "title": "Seeking Guidance for Simple yet effective approch for ABSA for my FYP · Issue...",
    "count": 78,
    "uniques": 25
  },
  {
    "path": "/yangheng95/PyABSA/tree/v2/docs",
    "title": "PyABSA/docs at v2 · yangheng95/PyABSA · GitHub",
    "count": 71,
    "uniques": 21
  },
  {
    "path": "/yangheng95/PyABSA/blob/v2/examples-v2/aspect_opinion_sentiment_category_extraction/inference.py",
    "title": "PyABSA/examples-v2/aspect_opinion_sentiment_category_extraction/inference.py ...",
    "count": 69,
    "uniques": 15
  }
]