{
  "count": 3082,
  "uniques": 287,
  "views": [
    {
      "timestamp": "2024-06-23T00:00:00Z",
      "count": 740,
      "uniques": 34
    },
    {
      "timestamp": "2024-06-24T00:00:00Z",
      "count": 818,
      "uniques": 68
    },
    {
      "timestamp": "2024-06-25T00:00:00Z",
      "count": 376,
      "uniques": 40
    },
    {
      "timestamp": "2024-06-26T00:00:00Z",
      "count": 378,
      "uniques": 43
    },
    {
      "timestamp": "2024-06-27T00:00:00Z",
      "count": 298,
      "uniques": 44
    },
    {
      "timestamp": "2024-06-28T00:00:00Z",
      "count": 365,
      "uniques": 40
    },
    {
      "timestamp": "2024-06-29T00:00:00Z",
      "count": 107,
      "uniques": 18
    }
  ]
}